CHANGELOG.md
LICENSE
MANIFEST.in
README.md
setup.cfg
setup.py
versioneer.py
src/libreflow/__init__.py
src/libreflow.rouge.egg-info/PKG-INFO
src/libreflow.rouge.egg-info/SOURCES.txt
src/libreflow.rouge.egg-info/dependency_links.txt
src/libreflow.rouge.egg-info/requires.txt
src/libreflow.rouge.egg-info/top_level.txt
src/libreflow/rouge/__init__.py
src/libreflow/rouge/_version.py
src/libreflow/rouge/gui.py
src/libreflow/rouge/session.py
src/libreflow/rouge/custom_home/__init__.py
src/libreflow/rouge/custom_home/ui.py
src/libreflow/rouge/flow/__init__.py
src/libreflow/rouge/flow/entity_manager.py
src/libreflow/rouge/flow/file.py
src/libreflow/rouge/flow/film.py
src/libreflow/rouge/flow/runners.py
src/libreflow/rouge/flow/shot.py
src/libreflow/rouge/flow/site.py
src/libreflow/rouge/flow/task.py
src/libreflow/rouge/flow/users.py
src/libreflow/rouge/resources/__init__.py
src/libreflow/rouge/resources/file_templates/__init__.py
src/libreflow/rouge/resources/file_templates/template.houdoo
src/libreflow/rouge/resources/file_templates/template.plas
src/libreflow/rouge/resources/icons/__init__.py
src/libreflow/rouge/resources/icons/gui/__init__.py
src/libreflow/rouge/resources/icons/gui/comment-lines.png
src/libreflow/rouge/resources/icons/gui/houdoo.png
src/libreflow/rouge/resources/icons/gui/plas.png
src/libreflow/rouge/ui/__init__.py
src/libreflow/rouge/ui/package.py
src/libreflow/rouge/ui/importfiles/__init__.py
src/libreflow/rouge/ui/importfiles/custom_widget.py
src/libreflow/rouge/ui/importfiles/shot_list.py