Metadata-Version: 2.1
Name: libreflow.rouge
Version: 2.0.12
Summary: A rouge flow
Home-page: https://gitlab.com/lfs.coop/libreflow/libreflow.rouge
Author: Flavio Perez
Author-email: flavio@lfs.coop
License: LGPLv3+
Keywords: kabaret cgwire kitsu gazu animation pipeline libreflow
Classifier: Programming Language :: Python :: 3
Classifier: Intended Audience :: Developers
Classifier: Intended Audience :: End Users/Desktop
Classifier: Intended Audience :: Information Technology
Classifier: License :: OSI Approved :: GNU Lesser General Public License v3 or later (LGPLv3+)
Classifier: Operating System :: OS Independent
Requires-Python: >=3.7
License-File: LICENSE
